{
  "projects": [
    {
      "id": 1,
      "title": "Package tracker",
      "techStack": ["React", "JavaScript", "HTML", "CSS", "Recoil"],
      "imageFileName": "package-tracker.png",
      "repoLink": "https://github.com/eeels22/package-tracker",
      "hostedLink": "https://package-tracker-sda9.web.app/",
      "description": "An app that displays a list of tracked parcels fetched from an API endpoint. Select information in English or Swedish language."
    },
    {
      "id": 2,
      "title": "EIKA shopping list",
      "techStack": ["React", "TypeScript", "HTML", "CSS"],
      "imageFileName": "package-tracker.png",
      "repoLink": "https://github.com/eeels22/eika-shopping-list",
      "hostedLink": "https://eika-shopping-list-ts.web.app/",
      "description": "A shopping list app that lets users keep track of things to buy at the store."
    },
    {
      "id": 3,
      "title": "Cuddly",
      "techStack": [
        "React",
        "HTML",
        "CSS",
        "Java",
        "Spring",
        "Postgres",
        "Hibernate"
      ],
      "imageFileName": "package-tracker.png",
      "repoLink": "https://github.com/eeels22/cuddly",
      "hostedLink": "",
      "description": "Cuddly is a prototype social media platform for everything pet related"
    },
    {
      "id": 4,
      "title": "Social media dashboard",
      "techStack": ["React", "HTML", "CSS"],
      "imageFileName": "package-tracker.png",
      "repoLink": "https://github.com/eeels22/dashboard-theme-toggle",
      "hostedLink": "",
      "description": "My solution to the 'Social media dashboard with theme switcher' challenge on Frontend Mentor."
    }
  ]
}
